api.py
fastauth/__init__.py
fastauth/app.py
fastauth/client_db/client_db.py
fastauth/config/__init__.py
fastauth/config/logger.py
fastauth/config/server.py
fastauth/middleware/__init__.py
fastauth/middleware/middleware.py
fastauth/middleware/utils.py
fastauth/middleware/websocket.py
fastauth/models/responses/standart.py
fastauth/openapi/__init__.py
fastauth/openapi/openapi.py
fastauth/routers/__init__.py
fastauth/routers/auth.py
fastauth/utils/__init__.py
fastauth/utils/cryptography_key.py
fastauth/utils/decode_token.py
fastauth/utils/envfile.py
fastauth_api-0.0.4.dist-info/licenses/LICENSE
fastauth_api-0.0.4.dist-info/METADATA
fastauth_api-0.0.4.dist-info/WHEEL
fastauth_api-0.0.4.dist-info/top_level.txt
fastauth_api-0.0.4.dist-info/RECORD
