Metadata-Version: 2.4
Name: fastauth-api
Version: 0.0.4
Author-email: Raúl Beltrán Gómez <rb58853@gmail.com>
License-Expression: MIT
Project-URL: Homepage, https://github.com/rb58853/fastauth-api
Project-URL: Issues, https://github.com/rb58853/fastauth-api/issues
Classifier: Programming Language :: Python :: 3
Classifier: Operating System :: OS Independent
Requires-Python: >=3.11
License-File: LICENSE
Requires-Dist: fastapi
Requires-Dist: websockets
Requires-Dist: requests
Requires-Dist: python-jose[cryptography]
Requires-Dist: cryptography
Requires-Dist: uvicorn
Dynamic: license-file
